MDToolbox/MDToolbox.py
MDToolbox/__init__.py
MDToolbox-0.1.dist-info/DESCRIPTION.rst
MDToolbox-0.1.dist-info/METADATA
MDToolbox-0.1.dist-info/RECORD
MDToolbox-0.1.dist-info/WHEEL
MDToolbox-0.1.dist-info/metadata.json
MDToolbox-0.1.dist-info/top_level.txt
