Metadata-Version: 2.0
Name: MDToolbox
Version: 0.1
Summary: Toolbox for online analysis
Home-page: https://github.com/apoyet/MDToolbox
Author: Axel Poyet
Author-email: axel.poyet@gmail.com
License: MIT
Keywords: Toolbox
Platform: UNKNOWN
